extendedmosaicperm/__init__.py
extendedmosaicperm/factor.py
extendedmosaicperm/factor_data.py
extendedmosaicperm/tilings.py
extendedmosaicperm/experiments/__init__.py
extendedmosaicperm/experiments/adaptive_tiling.py
extendedmosaicperm/experiments/base.py
extendedmosaicperm/experiments/plotting.py
extendedmosaicperm/experiments/ridge.py
extendedmosaicperm/experiments/sign_flip.py
extendedmosaicperm/tests/test_experiments_smoke.py
extendedmosaicperm/tests/test_factor.py
extendedmosaicperm/tests/test_factor_data.py
extendedmosaicperm/tests/test_tilings.py
extendedmosaicperm-0.1.0.dist-info/licenses/LICENSE
extendedmosaicperm-0.1.0.dist-info/METADATA
extendedmosaicperm-0.1.0.dist-info/WHEEL
extendedmosaicperm-0.1.0.dist-info/top_level.txt
extendedmosaicperm-0.1.0.dist-info/RECORD
